{
  "parent": "minecraft:recipes/root",
  "rewards": {
    "recipes": [
      "em:full_moon"
    ]
  },
  "criteria": {
    "has_hydragenum": {
      "trigger": "minecraft:inventory_changed",
      "conditions": {
        "items": [
          {
            "item": "em:hydragenum"
          }
        ]
      }
    },
    "has_quebrith": {
      "trigger": "minecraft:inventory_changed",
      "conditions": {
        "items": [
          {
            "item": "em:quebrith"
          }
        ]
      }
    },
    "has_vermilion": {
      "trigger": "minecraft:inventory_changed",
      "conditions": {
        "items": [
          {
            "item": "em:vermilion"
          }
        ]
      }
    }
  },
  "requirements": [
    [
      "has_hydragenum",
      "has_quebrith",
      "has_vermilion"
    ]
  ]
}